sequential_tar/__init__.py
sequential_tar/base.py
sequential_tar/version.py
sequential_tar-0.0.4.dist-info/LICENSE
sequential_tar-0.0.4.dist-info/METADATA
sequential_tar-0.0.4.dist-info/WHEEL
sequential_tar-0.0.4.dist-info/top_level.txt
sequential_tar-0.0.4.dist-info/RECORD
