Metadata-Version: 2.1
Name: sequential_tar
Version: 0.0.4
Summary: Write and read tape archives (tar) sequentially.
Home-page: https://github.com/cherenkov-plenoscope/sequential_tar
Author: Sebastian A. Mueller
Author-email: sebastian-achim.mueller@mpi-hd.mpg.de
Classifier: Programming Language :: Python :: 3
Classifier: License :: OSI Approved :: MIT License
Classifier: Operating System :: OS Independent
Classifier: Natural Language :: English
License-File: LICENSE
